README.md
setup.cfg
setup.py
anonymizer/__init__.py
anonymizer/anonymize.py
anonymizer/faker_type.py
data_anonymizer_mapper.egg-info/PKG-INFO
data_anonymizer_mapper.egg-info/SOURCES.txt
data_anonymizer_mapper.egg-info/dependency_links.txt
data_anonymizer_mapper.egg-info/requires.txt
data_anonymizer_mapper.egg-info/top_level.txt
data_anonymizer_mapper.egg-info/zip-safe