Metadata-Version: 1.2
Name: data-anonymizer-mapper
Version: 0.1.0
Summary: Anonymizer is a Python package that generates fake data for you, especially useful with pandas dataframes.
Home-page: https://github.com/samiriff/anonymizer
Author: samiriff
Author-email: samiriff@gmail.com
License: MIT License
Download-URL: https://github.com/samiriff/anonymizer/archive/0.1.0.tar.gz
Keywords: faker anonymizer data test mock generator pandas dataframe anonymize
Platform: any
Classifier: Development Status :: 5 - Production/Stable
Classifier: Intended Audience :: Developers
Classifier: Programming Language :: Python
Classifier: Programming Language :: Python :: 2
Classifier: Programming Language :: Python :: 2.7
Classifier: Programming Language :: Python :: 3
Classifier: Programming Language :: Python :: 3.4
Classifier: Programming Language :: Python :: 3.5
Classifier: Programming Language :: Python :: 3.6
Classifier: Programming Language :: Python :: 3.7
Classifier: Programming Language :: Python :: Implementation :: CPython
Classifier: Programming Language :: Python :: Implementation :: PyPy
Classifier: Topic :: Software Development :: Libraries :: Python Modules
Classifier: Topic :: Software Development :: Testing
Classifier: Topic :: Utilities
Classifier: License :: OSI Approved :: MIT License
Requires-Python: >=2.7, !=3.0.*, !=3.1.*, !=3.2.*, !=3.3.*
